gptools/stan/__init__.py
gptools/stan/__main__.py
gptools/stan/gptools/fft.stan
gptools/stan/gptools/fft1.stan
gptools/stan/gptools/fft2.stan
gptools/stan/gptools/graph.stan
gptools/stan/gptools/util.stan
tests/conftest.py
tests/test_examples.py
tests/test_main.py
tests/test_stan_functions.py
gptools_stan-1.0.0.dist-info/METADATA
gptools_stan-1.0.0.dist-info/WHEEL
gptools_stan-1.0.0.dist-info/top_level.txt
gptools_stan-1.0.0.dist-info/RECORD
