Metadata-Version: 2.2
Name: gptools-stan
Version: 1.0.0
Summary: Gaussian processes on graphs and lattices in Stan.
Author: Till Hoffmann, Jukka-Pekka Onnela
Project-URL: Documentation, https://gptools-stan.readthedocs.io
Project-URL: Repository, https://github.com/onnela-lab/gptools.git
Project-URL: Issues, https://github.com/onnela-lab/gptools/issues
Project-URL: Reference, https://doi.org/10.18637/jss.v112.i02
Keywords: Gaussian process,Stan,Bayesian inference,graph,Fourier
Classifier: Development Status :: 5 - Production/Stable
Classifier: Programming Language :: Python :: 3
Classifier: Intended Audience :: Science/Research
Classifier: License :: OSI Approved :: MIT License
Classifier: Topic :: Scientific/Engineering
Requires-Python: >=3.8
Requires-Dist: cmdstanpy>=1.0.7
Requires-Dist: numpy
